[
    {
        "total": 5391779843,
        "name": "http://www.w3.org/1999/02/22-rdf-syntax-ns#type"
    },
    {
        "total": 2867340956,
        "name": "http://schema.org/description"
    },
    {
        "total": 1639125082,
        "name": "http://purl.org/spar/cito/cites"
    },
    {
        "total": 1468919125,
        "name": "http://wikiba.se/ontology#rank"
    },
    {
        "total": 1343732919,
        "name": "http://www.w3.org/2000/01/rdf-schema#label"
    },
    {
        "total": 1210220213,
        "name": "http://www.w3.org/ns/prov#wasDerivedFrom"
    },
    {
        "total": 810724875,
        "name": "http://purl.org/dc/terms/creator"
    },
    {
        "total": 677354397,
        "name": "http://prismstandard.org/namespaces/basic/2.0/keyword"
    },
    {
        "total": 562545782,
        "name": "http://www.w3.org/2002/07/owl#sameAs"
    },
    {
        "total": 465161388,
        "name": "http://schema.org/relatedDrug"
    },
    {
        "total": 426031460,
        "name": "http://purl.org/dc/terms/created"
    },
    {
        "total": 420064959,
        "name": "http://purl.org/dc/terms/subject"
    },
    {
        "total": 398919388,
        "name": "http://purl.org/spar/fabio/hasURL"
    },
    {
        "total": 390862003,
        "name": "https://makg.org/property/citationCount"
    },
    {
        "total": 390845861,
        "name": "https://makg.org/property/rank"
    },
    {
        "total": 385509413,
        "name": "http://dbpedia.org/ontology/wikiPageWikiLink"
    },
    {
        "total": 379071209,
        "name": "http://purl.org/dc/terms/title"
    },
    {
        "total": 289423663,
        "name": "http://www.wikidata.org/prop/P2860"
    },
    {
        "total": 289423544,
        "name": "http://www.wikidata.org/prop/statement/P2860"
    },
    {
        "total": 289375256,
        "name": "http://www.wikidata.org/prop/direct/P2860"
    },
    {
        "total": 238670900,
        "name": "https://makg.org/property/referenceCount"
    },
    {
        "total": 238670900,
        "name": "https://makg.org/property/estimatedCitationCount"
    },
    {
        "total": 238664917,
        "name": "http://prismstandard.org/namespaces/basic/2.0/publicationDate"
    },
    {
        "total": 236924540,
        "name": "http://schema.org/about"
    },
    {
        "total": 234130213,
        "name": "http://purl.org/spar/c4o/hasContext"
    },
    {
        "total": 228379835,
        "name": "http://www.w3.org/ns/oa#hasBody"
    },
    {
        "total": 197856906,
        "name": "http://www.w3.org/2004/02/skos/core#altLabel"
    },
    {
        "total": 196302451,
        "name": "http://nextprot.org/rdf#reference"
    },
    {
        "total": 192791750,
        "name": "http://nextprot.org/rdf#provenance"
    },
    {
        "total": 192791750,
        "name": "http://nextprot.org/rdf#accession"
    },
    {
        "total": 171451413,
        "name": "http://xmlns.com/foaf/0.1/name"
    },
    {
        "total": 168215221,
        "name": "http://www.wikidata.org/prop/qualifier/P1545"
    },
    {
        "total": 167995501,
        "name": "http://nextprot.org/rdf#evidence"
    },
    {
        "total": 161819408,
        "name": "http://purl.org/spar/cito/hasCitedEntity"
    },
    {
        "total": 161819408,
        "name": "http://purl.org/spar/cito/hasCitingEntity"
    },
    {
        "total": 158551961,
        "name": "http://www.w3.org/ns/oa#hasTarget"
    },
    {
        "total": 152191103,
        "name": "https://makg.org/property/paperFamilyCount"
    },
    {
        "total": 152174961,
        "name": "https://makg.org/property/paperCount"
    },
    {
        "total": 150576715,
        "name": "http://www.w3.org/ns/prov#wasGeneratedBy"
    },
    {
        "total": 150088419,
        "name": "http://www.w3.org/2000/01/rdf-schema#isDefinedBy"
    },
    {
        "total": 149624506,
        "name": "http://www.w3.org/ns/oa#hasSelector"
    },
    {
        "total": 149624506,
        "name": "http://www.w3.org/ns/oa#hasSource"
    },
    {
        "total": 149602586,
        "name": "http://www.w3.org/ns/oa#exact"
    },
    {
        "total": 148593294,
        "name": "http://www.w3.org/ns/oa#start"
    },
    {
        "total": 140423336,
        "name": "http://www.w3.org/ns/oa#end"
    },
    {
        "total": 140293526,
        "name": "http://purl.org/dc/terms/abstract"
    },
    {
        "total": 140190635,
        "name": "http://purl.org/allie/ontology/201108#hasMemberOf"
    },
    {
        "total": 139227097,
        "name": "http://purl.org/spar/fabio/hasDiscipline"
    },
    {
        "total": 134502742,
        "name": "http://purl.org/dc/terms/identifier"
    },
    {
        "total": 134418091,
        "name": "http://www.wikidata.org/prop/P2093"
    }
]